<?xml version = '1.0' encoding = 'UTF-8'?>
<Diagram class="oracle.dbtools.crest.swingui.logical.DPVLogical" name="Logical" id="679FAE68-C9C1-7A3D-5C76-2CAAAE4E4CB5">
<createdBy>mkutz</createdBy>
<modifiedBy>mkutz</modifiedBy>
<createdTime>2020-10-26 13:29:24 UTC</createdTime>
<autoRoute>false</autoRoute>
<boxInbox>true</boxInbox>
<showLegend>false</showLegend>
<showLabels>false</showLabels>
<showRelAttributes>false</showRelAttributes>
<gridEnabled>false</gridEnabled>
<showGrid>false</showGrid>
<diagramColor>-1</diagramColor>
<display>false</display>
<notation>1</notation>
<objectViews>
<OView class="oracle.dbtools.crest.swingui.logical.TVEntity" oid="0C103F38-AA06-8B0F-C4E0-B6647DB8D447" otype="Entity" vid="87F4BC67-3DA4-1362-9562-6F606F664AC0">
<hideElementsInCurrentOnly>false</hideElementsInCurrentOnly>
<bounds x="8" y="71" width="196" height="71"/>
</OView>
<OView class="oracle.dbtools.crest.swingui.logical.TVEntity" oid="31526D98-C856-F44D-8270-71D0529C04AC" otype="Entity" vid="A62BD045-71E2-CA1A-2D2D-C2FAD750BECB">
<hideElementsInCurrentOnly>false</hideElementsInCurrentOnly>
<bounds x="80" y="458" width="116" height="57"/>
</OView>
<OView class="oracle.dbtools.crest.swingui.logical.TVEntity" oid="366D0392-6B64-70D4-193B-50C67FAE2256" otype="Entity" vid="22962450-B7CC-D43A-4619-486C35BE5CF2">
<hideElementsInCurrentOnly>false</hideElementsInCurrentOnly>
<bounds x="266" y="60" width="190" height="118"/>
</OView>
<OView class="oracle.dbtools.crest.swingui.logical.TVEntity" oid="62318D69-1480-4D3B-B83D-DFC29A0C1EE1" otype="Entity" vid="F610E1C4-20A9-A819-7802-FFC89C5D5529">
<hideElementsInCurrentOnly>false</hideElementsInCurrentOnly>
<bounds x="1134" y="665" width="214" height="50"/>
</OView>
<OView class="oracle.dbtools.crest.swingui.logical.TVEntity" oid="68AB0007-363E-CB93-370F-E1AD4E404EAD" otype="Entity" vid="33113726-9E9B-FE8C-9ECC-CA5C7C5D72EC">
<hideElementsInCurrentOnly>false</hideElementsInCurrentOnly>
<bounds x="582" y="507" width="221" height="142"/>
</OView>
<OView class="oracle.dbtools.crest.swingui.logical.TVEntity" oid="6BB76B61-AAC3-CF04-484E-E8AE29A556D9" otype="Entity" vid="7865EE29-04B1-6A0C-4EBB-DA2E488CEA74">
<hideElementsInCurrentOnly>false</hideElementsInCurrentOnly>
<bounds x="517" y="64" width="211" height="66"/>
</OView>
<OView class="oracle.dbtools.crest.swingui.logical.TVEntity" oid="6EA65B75-8EBB-CF9A-A69B-26D52A29E9F2" otype="Entity" vid="B15E135C-EEA7-6BE0-1FF2-F002FC3C5903">
<hideElementsInCurrentOnly>false</hideElementsInCurrentOnly>
<bounds x="402" y="295" width="307" height="99"/>
</OView>
<OView class="oracle.dbtools.crest.swingui.logical.TVEntity" oid="6EAAB231-BC7A-12B9-5DA2-8F8EDF1E166B" otype="Entity" vid="5BBC4C6F-D103-AED8-F339-59C2083ED77C">
<hideElementsInCurrentOnly>false</hideElementsInCurrentOnly>
<bounds x="858" y="506" width="175" height="47"/>
</OView>
<OView class="oracle.dbtools.crest.swingui.logical.TVEntity" oid="744024CB-9C22-367B-A075-D9A21A979428" otype="Entity" vid="ECE47E7D-71B6-378F-B407-DDE6401F76DB">
<hideElementsInCurrentOnly>false</hideElementsInCurrentOnly>
<bounds x="83" y="335" width="163" height="59"/>
</OView>
<OView class="oracle.dbtools.crest.swingui.logical.TVEntity" oid="7DE6B3F9-42E7-2AF4-569E-243AC9C5D075" otype="Entity" vid="8B1E4A48-1FED-E400-16E9-8E535419A40B">
<hideElementsInCurrentOnly>false</hideElementsInCurrentOnly>
<bounds x="236" y="641" width="289" height="89"/>
</OView>
<OView class="oracle.dbtools.crest.swingui.logical.TVEntity" oid="A77C43FE-511E-144A-4074-41DA27D76B9A" otype="Entity" vid="C5D31B57-DFCF-B6E4-E2BA-371E83ED033B">
<hideElementsInCurrentOnly>false</hideElementsInCurrentOnly>
<bounds x="990" y="221" width="227" height="74"/>
</OView>
<OView class="oracle.dbtools.crest.swingui.logical.TVEntity" oid="AE863B77-7A42-72B3-8A02-01B8BCCB5E27" otype="Entity" vid="D943CE40-A977-C365-DA60-64D1BC0AC0EB">
<hideElementsInCurrentOnly>false</hideElementsInCurrentOnly>
<bounds x="778" y="63" width="285" height="104"/>
</OView>
<OView class="oracle.dbtools.crest.swingui.logical.TVEntity" oid="CB1AA442-B782-8997-F72A-8748D7E73493" otype="Entity" vid="93CA491D-5A82-3294-04C0-8A7C07F5872E">
<hideElementsInCurrentOnly>false</hideElementsInCurrentOnly>
<bounds x="1139" y="562" width="208" height="50"/>
</OView>
<OView class="oracle.dbtools.crest.swingui.logical.TVEntity" oid="EE881C36-53AA-03EC-A8C5-AE0ED8915B79" otype="Entity" vid="8BF74D7B-866E-548A-30FE-EDC59A9068F7">
<hideElementsInCurrentOnly>false</hideElementsInCurrentOnly>
<bounds x="70" y="305" width="248" height="242"/>
</OView>
<OView class="oracle.dbtools.crest.swingui.logical.TVEntity" oid="F0A7F3D0-F315-B915-2EC5-504AD46A66C2" otype="Entity" vid="03E195F3-ACE4-5BE6-8AE9-5406D5DEAB0C">
<hideElementsInCurrentOnly>false</hideElementsInCurrentOnly>
<bounds x="1113" y="525" width="355" height="235"/>
</OView>
<OView class="oracle.dbtools.crest.swingui.logical.TVEntity" oid="F61491A6-4F48-1EE7-D72C-8344AAF9EADF" otype="Entity" vid="4C9E5391-9625-E11B-F82B-E99FEC18ACC7">
<hideElementsInCurrentOnly>false</hideElementsInCurrentOnly>
<bounds x="80" y="401" width="160" height="55"/>
</OView>
</objectViews>
<connectors>
<Connector class="oracle.dbtools.crest.swingui.logical.TVRelation" oid="07B54725-DA7D-A4F7-E5AD-A535688A61D7" otype="Relation" vid_source="5BBC4C6F-D103-AED8-F339-59C2083ED77C" vid_target="33113726-9E9B-FE8C-9ECC-CA5C7C5D72EC">
<hideElementsInCurrentOnly>false</hideElementsInCurrentOnly>
<backgroundColor>-16777216</backgroundColor>
<lineWidth>1</lineWidth>
<points>
<point x="858" y="530"/>
<point x="803" y="530"/>
</points>
</Connector>
<Connector class="oracle.dbtools.crest.swingui.logical.TVInheritanceRelation" oid="0D07E722-4E67-00B0-1D9C-7E9322C27ED0" otype="Hierarchy relation" vid_source="03E195F3-ACE4-5BE6-8AE9-5406D5DEAB0C" vid_target="F610E1C4-20A9-A819-7802-FFC89C5D5529">
<hideElementsInCurrentOnly>false</hideElementsInCurrentOnly>
<backgroundColor>-65536</backgroundColor>
<lineWidth>1</lineWidth>
</Connector>
<Connector class="oracle.dbtools.crest.swingui.logical.TVRelation" oid="297C5033-4BD4-477B-9CF9-15492D9CC9BB" otype="Relation" vid_source="8B1E4A48-1FED-E400-16E9-8E535419A40B" vid_target="33113726-9E9B-FE8C-9ECC-CA5C7C5D72EC">
<hideElementsInCurrentOnly>false</hideElementsInCurrentOnly>
<backgroundColor>-16777216</backgroundColor>
<lineWidth>1</lineWidth>
<points>
<point x="525" y="645"/>
<point x="582" y="645"/>
</points>
</Connector>
<Connector class="oracle.dbtools.crest.swingui.logical.TVRelation" oid="3CEE5F31-6015-65E3-22F0-782030312445" otype="Relation" vid_source="D943CE40-A977-C365-DA60-64D1BC0AC0EB" vid_target="33113726-9E9B-FE8C-9ECC-CA5C7C5D72EC">
<hideElementsInCurrentOnly>false</hideElementsInCurrentOnly>
<backgroundColor>-16777216</backgroundColor>
<lineWidth>1</lineWidth>
<points>
<point x="790" y="167"/>
<point x="790" y="507"/>
</points>
</Connector>
<Connector class="oracle.dbtools.crest.swingui.logical.TVRelation" oid="3ECD36EB-EBE0-92F4-3EAC-3591F474D8EF" otype="Relation" vid_source="8BF74D7B-866E-548A-30FE-EDC59A9068F7" vid_target="8B1E4A48-1FED-E400-16E9-8E535419A40B">
<hideElementsInCurrentOnly>false</hideElementsInCurrentOnly>
<backgroundColor>-16777216</backgroundColor>
<lineWidth>1</lineWidth>
<points>
<point x="277" y="547"/>
<point x="277" y="641"/>
</points>
</Connector>
<Connector class="oracle.dbtools.crest.swingui.logical.TVInheritanceRelation" oid="4C06ECAB-8B76-8860-7339-5AD80FEAD911" otype="Hierarchy relation" vid_source="8BF74D7B-866E-548A-30FE-EDC59A9068F7" vid_target="4C9E5391-9625-E11B-F82B-E99FEC18ACC7">
<hideElementsInCurrentOnly>false</hideElementsInCurrentOnly>
<backgroundColor>-65536</backgroundColor>
<lineWidth>1</lineWidth>
</Connector>
<Connector class="oracle.dbtools.crest.swingui.logical.TVInheritanceRelation" oid="4EF3D81F-729C-2F3A-40E8-868E8E4E7491" otype="Hierarchy relation" vid_source="03E195F3-ACE4-5BE6-8AE9-5406D5DEAB0C" vid_target="93CA491D-5A82-3294-04C0-8A7C07F5872E">
<hideElementsInCurrentOnly>false</hideElementsInCurrentOnly>
<backgroundColor>-65536</backgroundColor>
<lineWidth>1</lineWidth>
</Connector>
<Connector class="oracle.dbtools.crest.swingui.logical.TVRelation" oid="52EDF75B-28C7-A93A-6516-EC22E02488F5" otype="Relation" vid_source="8B1E4A48-1FED-E400-16E9-8E535419A40B" vid_target="F610E1C4-20A9-A819-7802-FFC89C5D5529">
<hideElementsInCurrentOnly>false</hideElementsInCurrentOnly>
<backgroundColor>-16777216</backgroundColor>
<lineWidth>1</lineWidth>
<points>
<point x="525" y="682"/>
<point x="1134" y="682"/>
</points>
</Connector>
<Connector class="oracle.dbtools.crest.swingui.logical.TVRelation" oid="551C647E-BDE9-BB86-DA00-8343B0CEDC1E" otype="Relation" vid_source="7865EE29-04B1-6A0C-4EBB-DA2E488CEA74" vid_target="B15E135C-EEA7-6BE0-1FF2-F002FC3C5903">
<hideElementsInCurrentOnly>false</hideElementsInCurrentOnly>
<backgroundColor>-16777216</backgroundColor>
<lineWidth>1</lineWidth>
<points>
<point x="613" y="130"/>
<point x="613" y="295"/>
</points>
</Connector>
<Connector class="oracle.dbtools.crest.swingui.logical.TVRelation" oid="55567C9C-1D63-4426-BFD8-97210CCDE562" otype="Relation" vid_source="D943CE40-A977-C365-DA60-64D1BC0AC0EB" vid_target="C5D31B57-DFCF-B6E4-E2BA-371E83ED033B">
<hideElementsInCurrentOnly>false</hideElementsInCurrentOnly>
<backgroundColor>-16777216</backgroundColor>
<lineWidth>1</lineWidth>
<points>
<point x="1026" y="167"/>
<point x="1026" y="221"/>
</points>
</Connector>
<Connector class="oracle.dbtools.crest.swingui.logical.TVRelation" oid="716CA762-55A6-C9FB-0397-3BA539535758" otype="Relation" vid_source="C5D31B57-DFCF-B6E4-E2BA-371E83ED033B" vid_target="03E195F3-ACE4-5BE6-8AE9-5406D5DEAB0C">
<hideElementsInCurrentOnly>false</hideElementsInCurrentOnly>
<backgroundColor>-16777216</backgroundColor>
<lineWidth>1</lineWidth>
<points>
<point x="1180" y="295"/>
<point x="1180" y="525"/>
</points>
</Connector>
<Connector class="oracle.dbtools.crest.swingui.logical.TVRelation" oid="876510D4-97F9-44C5-8811-3EDDAF43E5EC" otype="Relation" vid_source="87F4BC67-3DA4-1362-9562-6F606F664AC0" vid_target="22962450-B7CC-D43A-4619-486C35BE5CF2">
<hideElementsInCurrentOnly>false</hideElementsInCurrentOnly>
<backgroundColor>-16777216</backgroundColor>
<lineWidth>1</lineWidth>
<points>
<point x="204" y="76"/>
<point x="266" y="76"/>
</points>
</Connector>
<Connector class="oracle.dbtools.crest.swingui.logical.TVInheritanceRelation" oid="9854EA83-9C53-F859-B389-2DF65B6746C4" otype="Hierarchy relation" vid_source="8BF74D7B-866E-548A-30FE-EDC59A9068F7" vid_target="A62BD045-71E2-CA1A-2D2D-C2FAD750BECB">
<hideElementsInCurrentOnly>false</hideElementsInCurrentOnly>
<backgroundColor>-65536</backgroundColor>
<lineWidth>1</lineWidth>
</Connector>
<Connector class="oracle.dbtools.crest.swingui.logical.TVRelation" oid="9E14F631-F377-1FD0-EA21-37BE2B95ED26" otype="Relation" vid_source="D943CE40-A977-C365-DA60-64D1BC0AC0EB" vid_target="5BBC4C6F-D103-AED8-F339-59C2083ED77C">
<hideElementsInCurrentOnly>false</hideElementsInCurrentOnly>
<backgroundColor>-16777216</backgroundColor>
<lineWidth>1</lineWidth>
<points>
<point x="930" y="167"/>
<point x="930" y="506"/>
</points>
</Connector>
<Connector class="oracle.dbtools.crest.swingui.logical.TVInheritanceRelation" oid="A194CBA0-B112-D51F-9265-A8A099AD2F2D" otype="Hierarchy relation" vid_source="8BF74D7B-866E-548A-30FE-EDC59A9068F7" vid_target="ECE47E7D-71B6-378F-B407-DDE6401F76DB">
<hideElementsInCurrentOnly>false</hideElementsInCurrentOnly>
<backgroundColor>-65536</backgroundColor>
<lineWidth>1</lineWidth>
</Connector>
<Connector class="oracle.dbtools.crest.swingui.logical.TVRelation" oid="AE2088E6-224E-4181-2E39-A2AE44E55189" otype="Relation" vid_source="22962450-B7CC-D43A-4619-486C35BE5CF2" vid_target="B15E135C-EEA7-6BE0-1FF2-F002FC3C5903">
<hideElementsInCurrentOnly>false</hideElementsInCurrentOnly>
<backgroundColor>-16777216</backgroundColor>
<lineWidth>1</lineWidth>
<points>
<point x="429" y="178"/>
<point x="429" y="295"/>
</points>
</Connector>
<Connector class="oracle.dbtools.crest.swingui.logical.TVRelation" oid="B7CD1E84-F676-BAF5-7C97-B0FC300AB4E4" otype="Relation" vid_source="33113726-9E9B-FE8C-9ECC-CA5C7C5D72EC" vid_target="03E195F3-ACE4-5BE6-8AE9-5406D5DEAB0C">
<hideElementsInCurrentOnly>false</hideElementsInCurrentOnly>
<backgroundColor>-16777216</backgroundColor>
<lineWidth>1</lineWidth>
<points>
<point x="803" y="587"/>
<point x="1113" y="587"/>
</points>
</Connector>
<Connector class="oracle.dbtools.crest.swingui.logical.TVRelation" oid="D064234D-9440-3711-5240-25C3BF8465F6" otype="Relation" vid_source="8BF74D7B-866E-548A-30FE-EDC59A9068F7" vid_target="B15E135C-EEA7-6BE0-1FF2-F002FC3C5903">
<hideElementsInCurrentOnly>false</hideElementsInCurrentOnly>
<backgroundColor>-16777216</backgroundColor>
<lineWidth>1</lineWidth>
<points>
<point x="318" y="354"/>
<point x="402" y="353"/>
</points>
</Connector>
<Connector class="oracle.dbtools.crest.swingui.logical.TVRelation" oid="F96BD8B5-7857-2DA7-09EB-CA048DF16889" otype="Relation" vid_source="B15E135C-EEA7-6BE0-1FF2-F002FC3C5903" vid_target="33113726-9E9B-FE8C-9ECC-CA5C7C5D72EC">
<hideElementsInCurrentOnly>false</hideElementsInCurrentOnly>
<backgroundColor>-16777216</backgroundColor>
<lineWidth>1</lineWidth>
<points>
<point x="615" y="394"/>
<point x="615" y="507"/>
</points>
</Connector>
<Connector class="oracle.dbtools.crest.swingui.logical.TVRelation" oid="FCE6FEC9-3F75-DB2B-3BC0-CC071E40E696" otype="Relation" vid_source="5BBC4C6F-D103-AED8-F339-59C2083ED77C" vid_target="03E195F3-ACE4-5BE6-8AE9-5406D5DEAB0C">
<hideElementsInCurrentOnly>false</hideElementsInCurrentOnly>
<backgroundColor>-16777216</backgroundColor>
<lineWidth>1</lineWidth>
<points>
<point x="1033" y="539"/>
<point x="1113" y="539"/>
</points>
</Connector>
</connectors>
</Diagram>